simpleitem/__init__.py
simpleitem/simpleitem.py
simpleitem-0.0.2.dist-info/LICENSE
simpleitem-0.0.2.dist-info/METADATA
simpleitem-0.0.2.dist-info/WHEEL
simpleitem-0.0.2.dist-info/top_level.txt
simpleitem-0.0.2.dist-info/RECORD
