Metadata-Version: 2.1
Name: simpleitem
Version: 0.0.2
Summary: A simple simple item
Home-page: https://github.com/dinceraslancom/simpleitem
Author: Dincer Aslan
Author-email: dinceraslan.com@gmail.com
License: UNKNOWN
Project-URL: Source, https://github.com/dinceraslancom/simpleitem
Platform: UNKNOWN
Classifier: Programming Language :: Python :: 3
Classifier: License :: OSI Approved :: MIT License
Classifier: Operating System :: OS Independent
Requires-Python: >=3.0
License-File: LICENSE
Requires-Dist: PyYAML (>=5.3.1)
